light_s3_client/__init__.py
light_s3_client/exceptions.py
light_s3_client/version.py
light_s3_client-0.0.30.dist-info/licenses/LICENSE
light_s3_client-0.0.30.dist-info/METADATA
light_s3_client-0.0.30.dist-info/WHEEL
light_s3_client-0.0.30.dist-info/top_level.txt
light_s3_client-0.0.30.dist-info/RECORD
